baboo_game/__init__.py
baboo_game/main.py
baboo_game/game/__init__.py
baboo_game/game/baboo_game.py
baboo_game/game/render_game.py
baboo_game/game/config/__init__.py
baboo_game/game/config/color_config.py
baboo_game/game/config/game_config.py
baboo_game/game/config/text_constant.py
baboo_game/game/library/__init__.py
baboo_game/game/library/abstract_dice.py
baboo_game-2.1.0.dist-info/LICENSE
baboo_game-2.1.0.dist-info/METADATA
baboo_game-2.1.0.dist-info/WHEEL
baboo_game-2.1.0.dist-info/top_level.txt
baboo_game-2.1.0.dist-info/RECORD
