Metadata-Version: 2.1
Name: baboo-game
Version: 2.1.0
Summary: A dice game prototype
Author-email: Vitalii Sili <vitaliisili@yahoo.com>
License: MIT License
Project-URL: homepage, https://github.com/vitaliisili/dice_game_python
Project-URL: documentation, https://github.com/vitaliisili/dice_game_python
Project-URL: repository, https://github.com/vitaliisili/dice_game_python
Keywords: dicegame,python,console game
Classifier: Development Status :: 3 - Alpha
Classifier: Intended Audience :: Education
Classifier: Programming Language :: Python :: 3
Classifier: License :: OSI Approved :: MIT License
Classifier: Operating System :: OS Independent
Requires-Python: >=3.10
License-File: LICENSE
Requires-Dist: colorama (>=0.4.6)
